example_demo/__init__.py
example_demo/__version__.py
example_demo/configuration.py
example_demo/configuration_ori.py
example_demo/default_setting.py
example_demo/eg_one.py
example_demo/exceptions.py
example_demo/readme.md
example_demo/setting.py
example_demo/setting_demo.py
example_demo/source_get_cfg.py
example_demo/airflow_plugins/__init__.py
example_demo/airflow_plugins/workday.py
example_demo/commands/__init__.py
example_demo/commands/cmdline.py
example_demo/commands/create_builder.py
example_demo/commands/start_program.py
example_demo/commands/generate/__init__.py
example_demo/commands/generate/generate_project.py
example_demo/commons/__init__.py
example_demo/commons/common_cfg.py
example_demo/commons/common_fun.py
example_demo/monitor/__init__.py
example_demo/monitor/log.py
example_demo/monitor/monitor_decorator.py
example_demo/monitor/monitor_signal_alert.py
example_demo/monitor/pipeline_redis_remote.py
example_demo/mrjob/__init__.py
example_demo/mrjob/cat.py
example_demo/mrjob/conf.py
example_demo/mrjob/parse.py
example_demo/mrjob/py2.py
example_demo/mrjob/setup.py
example_demo/mrjob/util.py
example_demo/mrjob/fs/__init__.py
example_demo/mrjob/fs/base.py
example_demo/mrjob/fs/composite.py
example_demo/mrjob/fs/local.py
example_demo/program_process/__init__.py
example_demo/program_process/process_download_parse.py
example_demo/program_process/process_final_result.py
example_demo/program_process/process_ftp.py
example_demo/program_process/process_request.py
example_demo/program_process/process_result_report.py
example_demo/program_process/process_sftp.py
example_demo/program_process/process_source_base.py
example_demo/program_process/process_source_get_cfg.py
example_demo/program_process/process_sqlserver.py
example_demo/program_process/process_url.py
example_demo/program_process/process_url_source.py
example_demo/program_process/process_work.py
example_demo/request_downloader/__init__.py
example_demo/request_downloader/airflow_downloader_hooks.py
example_demo-1.0.9.dist-info/LICENSE
example_demo-1.0.9.dist-info/METADATA
example_demo-1.0.9.dist-info/WHEEL
example_demo-1.0.9.dist-info/entry_points.txt
example_demo-1.0.9.dist-info/top_level.txt
example_demo-1.0.9.dist-info/RECORD
