Metadata-Version: 2.1
Name: example-demo
Version: 1.0.9
Summary: A small example package test
Home-page: https://github.com/pypa/sampleproject
Author: nico_zhang
Author-email: zhangyf959427@gmail.com
License: UNKNOWN
Platform: win_amd64
Classifier: Programming Language :: Python :: 3
Classifier: License :: OSI Approved :: MIT License
Classifier: Operating System :: OS Independent
Requires-Python: >3.5
Requires-Dist: fabric
Requires-Dist: requests
Requires-Dist: cchardet
Requires-Dist: better-exceptions
Requires-Dist: loguru
Requires-Dist: w3lib
Requires-Dist: lxml
Requires-Dist: parsel
Requires-Dist: pandas
Requires-Dist: redis
Requires-Dist: tenacity
Requires-Dist: attrs (==20.3.0)
Requires-Dist: wheel
Requires-Dist: PyYAML
Requires-Dist: click (==7.1.2)
Requires-Dist: jinja2 (==2.11.3)
Requires-Dist: jdmssql
Requires-Dist: sqlalchemy (==1.4.9)
Requires-Dist: beautifulsoup4
Requires-Dist: markupsafe (==2.0.1)
Requires-Dist: mysqlclient (==2.1.0)
Requires-Dist: pymssql (==2.1.5)
